encoded_video/__init__.py
encoded_video/encoded_video.py
encoded_video/utils.py
EncodedUriVideo-0.0.3.1.dist-info/METADATA
EncodedUriVideo-0.0.3.1.dist-info/WHEEL
EncodedUriVideo-0.0.3.1.dist-info/top_level.txt
EncodedUriVideo-0.0.3.1.dist-info/RECORD
