Metadata-Version: 2.1
Name: EncodedUriVideo
Version: 0.0.3.1
Summary: Video utilities
Home-page: https://github.com/nateraw/encoded-video
Author: Nathan Raw
Author-email: naterawdata@gmail.com
Requires-Dist: av
Requires-Dist: iopath
Requires-Dist: numpy
